[
  {
    "id": 1,
    "customerId": "royhan",
    "name": "Mie Goreng",
    "description": "Very Tasty",
    "price": 10000,
    "quantity": 1,
    "staffId": "",
    "status": "ORDERED"
  },
  {
    "id": 2,
    "customerId": "royhan",
    "name": "Nasi Goreng",
    "description": "Kinda Tasty",
    "price": 12000,
    "quantity": 1,
    "staffId": "",
    "status": "ORDERED"
  },
  {
    "id": 3,
    "customerId": "phitonthel",
    "name": "Nasi Goreng",
    "description": "Kinda Tasty",
    "price": 12000,
    "quantity": 1,
    "staffId": "",
    "status": "DELIVERED"
  },
  {
    "customerId": 1652150824898,
    "name": "Mie Goreng",
    "description": "Very Tasty",
    "price": 10000,
    "quantity": 1,
    "staffId": "staff1",
    "id": 4,
    "status": "ORDERED"
  },
  {
    "customerId": 1652150824898,
    "name": "Nasi Goreng",
    "description": "Kinda Tasty",
    "price": 12000,
    "quantity": 1,
    "staffId": "staff1",
    "id": 5,
    "status": "ORDERED"
  },
  {
    "customerId": 1652150828759,
    "name": "Mie Goreng",
    "description": "Very Tasty",
    "price": 10000,
    "quantity": 1,
    "staffId": "staff1",
    "id": 6,
    "status": "DELIVERED"
  },
  {
    "customerId": 1652150828759,
    "name": "Nasi Goreng",
    "description": "Kinda Tasty",
    "price": 12000,
    "quantity": 1,
    "staffId": "staff1",
    "id": 7,
    "status": "DELIVERED"
  },
  {
    "customerId": 1652155861561,
    "name": "Nasi Goreng",
    "description": "Very Tasty",
    "price": 12000,
    "quantity": 0,
    "id": 8,
    "status": "ORDERED"
  },
  {
    "customerId": 1652155861561,
    "name": "Burger",
    "description": "Kinda Tasty",
    "price": 25000,
    "quantity": 0,
    "id": 9,
    "status": "ORDERED"
  },
  {
    "customerId": 1652155865903,
    "name": "Nasi Goreng",
    "description": "Very Tasty",
    "price": 12000,
    "quantity": 0,
    "id": 10,
    "status": "ORDERED"
  },
  {
    "customerId": 1652155865903,
    "name": "Burger",
    "description": "Kinda Tasty",
    "price": 25000,
    "quantity": 0,
    "id": 11,
    "status": "ORDERED"
  },
  {
    "customerId": 1652155868146,
    "name": "Nasi Goreng",
    "description": "Very Tasty",
    "price": 12000,
    "quantity": 0,
    "id": 12,
    "status": "ORDERED"
  },
  {
    "customerId": 1652155868146,
    "name": "Burger",
    "description": "Kinda Tasty",
    "price": 25000,
    "quantity": 0,
    "id": 13,
    "status": "ORDERED"
  },
  {
    "customerId": 1652157492910,
    "name": "Nasi Goreng",
    "description": "Very Tasty",
    "price": 12000,
    "quantity": 0,
    "id": 14,
    "status": "ORDERED"
  },
  {
    "customerId": 1652157492910,
    "name": "Burger",
    "description": "Kinda Tasty",
    "price": 25000,
    "quantity": 0,
    "id": 15,
    "status": "ORDERED"
  },
  {
    "customerId": 1652157966847,
    "name": "Nasi Goreng",
    "description": "Very Tasty",
    "price": 12000,
    "quantity": 1,
    "id": 16,
    "status": "ORDERED"
  },
  {
    "customerId": 1652157966847,
    "name": "Burger",
    "description": "Kinda Tasty",
    "price": 25000,
    "quantity": 3,
    "id": 17,
    "status": "ORDERED"
  },
  {
    "customerId": 1652158009863,
    "name": "Nasi Goreng",
    "description": "Very Tasty",
    "price": 12000,
    "quantity": 0,
    "id": 18,
    "status": "ORDERED"
  },
  {
    "customerId": 1652158009863,
    "name": "Burger",
    "description": "Kinda Tasty",
    "price": 25000,
    "quantity": 0,
    "id": 19,
    "status": "ORDERED"
  },
  {
    "customerId": 1652159490670,
    "name": "Nasi Goreng",
    "description": "Very Tasty",
    "price": 12000,
    "quantity": 0,
    "id": 20,
    "status": "ORDERED"
  },
  {
    "customerId": 1652159490670,
    "name": "Burger",
    "description": "Kinda Tasty",
    "price": 25000,
    "quantity": 0,
    "id": 21,
    "status": "ORDERED"
  },
  {
    "customerId": 1652159721108,
    "name": "Nasi Goreng",
    "description": "Very Tasty",
    "price": 12000,
    "quantity": 0,
    "id": 22,
    "status": "ORDERED"
  },
  {
    "customerId": 1652159721108,
    "name": "Burger",
    "description": "Kinda Tasty",
    "price": 25000,
    "quantity": 0,
    "id": 23,
    "status": "ORDERED"
  },
  {
    "customerId": 1652159888150,
    "name": "Nasi Goreng",
    "description": "Very Tasty",
    "price": 12000,
    "quantity": 0,
    "id": 24,
    "status": "ORDERED"
  },
  {
    "customerId": 1652159888150,
    "name": "Burger",
    "description": "Kinda Tasty",
    "price": 25000,
    "quantity": 0,
    "id": 25,
    "status": "ORDERED"
  },
  {
    "customerId": 1652160046997,
    "name": "Nasi Goreng",
    "description": "Very Tasty",
    "price": 12000,
    "quantity": 0,
    "id": 26,
    "status": "ORDERED"
  },
  {
    "customerId": 1652160046997,
    "name": "Burger",
    "description": "Kinda Tasty",
    "price": 25000,
    "quantity": 0,
    "id": 27,
    "status": "ORDERED"
  },
  {
    "customerId": 1652160486950,
    "name": "Nasi Goreng",
    "description": "Very Tasty",
    "price": 12000,
    "quantity": 0,
    "id": 28,
    "status": "ORDERED"
  },
  {
    "customerId": 1652160486950,
    "name": "Burger",
    "description": "Kinda Tasty",
    "price": 25000,
    "quantity": 0,
    "id": 29,
    "status": "ORDERED"
  },
  {
    "customerId": 1652160502792,
    "name": "Nasi Goreng",
    "description": "Very Tasty",
    "price": 12000,
    "quantity": 0,
    "id": 30,
    "status": "ORDERED"
  },
  {
    "customerId": 1652160502792,
    "name": "Burger",
    "description": "Kinda Tasty",
    "price": 25000,
    "quantity": 0,
    "id": 31,
    "status": "ORDERED"
  },
  {
    "customerId": 1652160592478,
    "name": "Nasi Goreng",
    "description": "Very Tasty",
    "price": 12000,
    "quantity": 0,
    "id": 32,
    "status": "ORDERED"
  },
  {
    "customerId": 1652160592478,
    "name": "Burger",
    "description": "Kinda Tasty",
    "price": 25000,
    "quantity": 0,
    "id": 33,
    "status": "ORDERED"
  },
  {
    "customerId": 1652160612051,
    "name": "Nasi Goreng",
    "description": "Very Tasty",
    "price": 12000,
    "quantity": 0,
    "id": 34,
    "status": "ORDERED"
  },
  {
    "customerId": 1652160612051,
    "name": "Burger",
    "description": "Kinda Tasty",
    "price": 25000,
    "quantity": 0,
    "id": 35,
    "status": "ORDERED"
  },
  {
    "customerId": 1652160626217,
    "name": "Nasi Goreng",
    "description": "Very Tasty",
    "price": 12000,
    "quantity": 0,
    "id": 36,
    "status": "ORDERED"
  },
  {
    "customerId": 1652160626217,
    "name": "Burger",
    "description": "Kinda Tasty",
    "price": 25000,
    "quantity": 0,
    "id": 37,
    "status": "ORDERED"
  },
  {
    "customerId": 1652160638961,
    "name": "Nasi Goreng",
    "description": "Very Tasty",
    "price": 12000,
    "quantity": 0,
    "id": 38,
    "status": "ORDERED"
  },
  {
    "customerId": 1652160638961,
    "name": "Burger",
    "description": "Kinda Tasty",
    "price": 25000,
    "quantity": 0,
    "id": 39,
    "status": "ORDERED"
  },
  {
    "customerId": 1652160677375,
    "name": "Nasi Goreng",
    "description": "Very Tasty",
    "price": 12000,
    "quantity": 0,
    "id": 40,
    "status": "ORDERED"
  },
  {
    "customerId": 1652160677375,
    "name": "Burger",
    "description": "Kinda Tasty",
    "price": 25000,
    "quantity": 0,
    "id": 41,
    "status": "ORDERED"
  },
  {
    "customerId": 1652160712268,
    "name": "Nasi Goreng",
    "description": "Very Tasty",
    "price": 12000,
    "quantity": 0,
    "id": 42,
    "status": "ORDERED"
  },
  {
    "customerId": 1652160712268,
    "name": "Burger",
    "description": "Kinda Tasty",
    "price": 25000,
    "quantity": 0,
    "id": 43,
    "status": "ORDERED"
  },
  {
    "customerId": 1652160716471,
    "name": "Nasi Goreng",
    "description": "Very Tasty",
    "price": 12000,
    "quantity": 0,
    "id": 44,
    "status": "ORDERED"
  },
  {
    "customerId": 1652160716471,
    "name": "Burger",
    "description": "Kinda Tasty",
    "price": 25000,
    "quantity": 0,
    "id": 45,
    "status": "ORDERED"
  },
  {
    "customerId": 1652160746512,
    "name": "Nasi Goreng",
    "description": "Very Tasty",
    "price": 12000,
    "quantity": 0,
    "id": 46,
    "status": "ORDERED"
  },
  {
    "customerId": 1652160746512,
    "name": "Burger",
    "description": "Kinda Tasty",
    "price": 25000,
    "quantity": 0,
    "id": 47,
    "status": "ORDERED"
  },
  {
    "customerId": 1652160772410,
    "name": "Nasi Goreng",
    "description": "Very Tasty",
    "price": 12000,
    "quantity": 0,
    "id": 48,
    "status": "ORDERED"
  },
  {
    "customerId": 1652160772410,
    "name": "Burger",
    "description": "Kinda Tasty",
    "price": 25000,
    "quantity": 0,
    "id": 49,
    "status": "ORDERED"
  },
  {
    "customerId": 1652160797144,
    "name": "Nasi Goreng",
    "description": "Very Tasty",
    "price": 12000,
    "quantity": 0,
    "id": 50,
    "status": "ORDERED"
  },
  {
    "customerId": 1652160797144,
    "name": "Burger",
    "description": "Kinda Tasty",
    "price": 25000,
    "quantity": 0,
    "id": 51,
    "status": "ORDERED"
  }
]